poetry_lock_package/__init__.py
poetry_lock_package/app.py
poetry_lock_package/util.py
poetry_lock_package-0.5.3.dist-info/METADATA
poetry_lock_package-0.5.3.dist-info/WHEEL
poetry_lock_package-0.5.3.dist-info/entry_points.txt
poetry_lock_package-0.5.3.dist-info/RECORD
