Metadata-Version: 2.3
Name: poetry-lock-package
Version: 0.5.3
Summary: Poetry lock package generator
Author: Bram Neijt
Author-email: bram@neijt.nl
Requires-Python: >=3.9.0
Classifier: Environment :: Console
Classifier: Intended Audience :: Developers
Classifier: License :: OSI Approved :: GNU General Public License v3 (GPLv3)
Classifier: Programming Language :: Python :: 3
Classifier: Programming Language :: Python :: 3.9
Classifier: Programming Language :: Python :: 3.10
Classifier: Programming Language :: Python :: 3.11
Classifier: Programming Language :: Python :: 3.12
Classifier: Programming Language :: Python :: 3.13
Classifier: Topic :: Software Development :: Build Tools
Requires-Dist: toml (>=0.10.1,<0.11.0)
Project-URL: Repository, https://github.com/bneijt/poetry-lock-package
